pairs_footprints_for_like.py
pairs_footprints_for_like-1.0.dist-info/METADATA
pairs_footprints_for_like-1.0.dist-info/RECORD
pairs_footprints_for_like-1.0.dist-info/WHEEL
pairs_footprints_for_like-1.0.dist-info/entry_points.txt
pairs_footprints_for_like-1.0.dist-info/top_level.txt
