Metadata-Version: 2.1
Name: pairs-footprints-for-like
Version: 1.0
Summary: paris leave footprints fro like from me
Home-page: UNKNOWN
Author: mao2009
License: BSD
Platform: UNKNOWN
Requires-Dist: selenium
